setup.py
FlynnID.egg-info/PKG-INFO
FlynnID.egg-info/SOURCES.txt
FlynnID.egg-info/dependency_links.txt
FlynnID.egg-info/entry_points.txt
FlynnID.egg-info/requires.txt
FlynnID.egg-info/top_level.txt
flynnid/__init__.py
flynnid/flynnid.py