Metadata-Version: 1.0
Name: FlynnID
Version: 0.3
Summary: Registers Selenium nodes to a Selenium Grid hub.
Home-page: https://github.com/davehunt/flynnid
Author: Dave Hunt
Author-email: dhunt@mozilla.com
License: UNKNOWN
Platform: UNKNOWN
Classifier: Development Status :: 4 - Beta
Classifier: Intended Audience :: Developers
Classifier: License :: OSI Approved :: Mozilla Public License 2.0 (MPL 2.0)
Classifier: Operating System :: POSIX
Classifier: Operating System :: Microsoft :: Windows
Classifier: Operating System :: MacOS :: MacOS X
Classifier: Topic :: Software Development :: Quality Assurance
Classifier: Topic :: Software Development :: Testing
Classifier: Topic :: Utilities
Classifier: Programming Language :: Python
